spider/__init__.py
spider/__main__.py
spider/utils/__init__.py
spider/utils/common.py
spider/utils/consumer.py
spider/utils/producer.py
esnt_intern_mini_spider_ymh-0.1.0.dist-info/LICENSE
esnt_intern_mini_spider_ymh-0.1.0.dist-info/METADATA
esnt_intern_mini_spider_ymh-0.1.0.dist-info/WHEEL
esnt_intern_mini_spider_ymh-0.1.0.dist-info/top_level.txt
esnt_intern_mini_spider_ymh-0.1.0.dist-info/zip-safe
esnt_intern_mini_spider_ymh-0.1.0.dist-info/RECORD
